hue_zigbee_encoding/__init__.py
hue_zigbee_encoding/py.typed
hue_zigbee_encoding-1.0.0.dist-info/licenses/LICENSE.md
hue_zigbee_encoding-1.0.0.dist-info/WHEEL
hue_zigbee_encoding-1.0.0.dist-info/METADATA
hue_zigbee_encoding-1.0.0.dist-info/RECORD
