Metadata-Version: 2.4
Name: hue-zigbee-encoding
Version: 1.0.0
Summary: Binary encoding and decoding of Zigbee messages for Hue lights
Author: Jacob Bandes-Storch
License-Expression: MIT
License-File: LICENSE.md
Requires-Python: >=3.10
Project-URL: donate, https://github.com/sponsors/jtbandes
Project-URL: issues, https://github.com/jtbandes/hue-zigbee-encoding/issues
Project-URL: source, https://github.com/jtbandes/hue-zigbee-encoding
